keyring_gcloud/__init__.py
keyring_gcloud-0.1.4.dist-info/LICENSE
keyring_gcloud-0.1.4.dist-info/METADATA
keyring_gcloud-0.1.4.dist-info/WHEEL
keyring_gcloud-0.1.4.dist-info/entry_points.txt
keyring_gcloud-0.1.4.dist-info/top_level.txt
keyring_gcloud-0.1.4.dist-info/RECORD
