Metadata-Version: 2.1
Name: keyring-gcloud
Version: 0.1.4
Summary: A keyring backend for Google Cloud Platform
Author: Tor Arvid Lund
License: MIT
Project-URL: Homepage, https://github.com/torarvid/keyring-gcloud
Project-URL: Bug Tracker, https://github.com/torarvid/keyring-gcloud/issues
Keywords: keyring,gcloud,google cloud
Classifier: Programming Language :: Python :: 3
Classifier: License :: OSI Approved :: MIT License
Classifier: Operating System :: OS Independent
Classifier: Intended Audience :: Developers
Classifier: Topic :: Security
Requires-Python: >=3.12
License-File: LICENSE
Requires-Dist: google-auth >=2.35.0
Requires-Dist: google >=3.0.0
Requires-Dist: keyring >=24.3.1
Requires-Dist: requests >=2.32.3
